phosx/__init__.py
phosx/activation_evidence.py
phosx/assets/joined_auc_prc_violinplots.png
phosx/assets/joined_auc_prc_violinplots.svg
phosx/assets/logo.png
phosx/assets/workflow.png
phosx/assets/workflow.svg
phosx/assets/workflow_old.png
phosx/cli.py
phosx/data/S_T_PSSM_score_quantiles.h5
phosx/data/S_T_PSSMs.h5
phosx/data/Y_PSSM_score_quantiles.h5
phosx/data/Y_PSSMs.h5
phosx/data/kinase_metadata.h5
phosx/data/kinase_metadata_annotated.h5
phosx/kinase_activity.py
phosx/make_seqrnk.py
phosx/pssm_enrichment.py
phosx/pssms.py
phosx/utils.py
phosx-0.20.1.dist-info/METADATA
phosx-0.20.1.dist-info/WHEEL
phosx-0.20.1.dist-info/entry_points.txt
phosx-0.20.1.dist-info/licenses/LICENSE
phosx-0.20.1.dist-info/RECORD
