Metadata-Version: 2.4
Name: phosx
Version: 0.20.1
Summary: Differential kinase activity inference from phosphosproteomics data
License-File: LICENSE
Author: Alessandro Lussana
Author-email: alussana@ebi.ac.uk
Requires-Python: >=3.10,<4.0
Classifier: Programming Language :: Python :: 3
Classifier: Programming Language :: Python :: 3.10
Classifier: Programming Language :: Python :: 3.11
Classifier: Programming Language :: Python :: 3.12
Classifier: Programming Language :: Python :: 3.13
Classifier: Programming Language :: Python :: 3.14
Requires-Dist: h5py (>=3.9.0,<4.0.0)
Requires-Dist: pandas (>=2.0.3,<3.0.0)
Requires-Dist: requests (>=2.32.3,<3.0.0)
Requires-Dist: seaborn (>=0.12.2,<0.13.0)
Requires-Dist: tables (>=3.9.2,<4.0.0)
Requires-Dist: tqdm (>=4.66.2,<5.0.0)
